envcheck/__init__.py
envcheck/envcheck.py
envcheck-0.0.9.dist-info/LICENSE
envcheck-0.0.9.dist-info/METADATA
envcheck-0.0.9.dist-info/WHEEL
envcheck-0.0.9.dist-info/entry_points.txt
envcheck-0.0.9.dist-info/top_level.txt
envcheck-0.0.9.dist-info/RECORD
