Metadata-Version: 2.1
Name: envcheck
Version: 0.0.9
Summary: A small, simple command line utility to check for, compare and merge environment variables between environment files and their .example counterparts
Home-page: https://github.com/dyspop/envcheck
Author: Dan Black
Author-email: dyspop@gmail.com
License: UNKNOWN
Project-URL: Bug Tracker, https://github.com/dyspop/dyspop/issues
Platform: UNKNOWN
Classifier: Programming Language :: Python :: 3
Classifier: License :: OSI Approved :: GNU Lesser General Public License v3 (LGPLv3)
Classifier: Operating System :: OS Independent
Requires-Python: >=3.6
License-File: LICENSE
